{
  "metadata": {
    "entity": "HelioForge Energy Systems",
    "export_id": "HF-CONTRACTVAULT-2026-07",
    "source_system": "ContractVault vendor register export",
    "prepared_by": "Procurement Operations",
    "classification": "Synthetic demo artifact"
  },
  "records": [
    {
      "vendor_id": "tensorgrid",
      "name": "TensorGrid Compute",
      "category": "infrastructure",
      "annual_cost": 185000,
      "monthly_cost": 15417,
      "renewal_date": "2026-07-08",
      "status": "pending_signature",
      "owner": "Platform",
      "termination_notice_days": 30,
      "auto_renew": true,
      "board_approved": false,
      "notes": "TensorGrid Compute export row from ContractVault; owner attestation pending.",
      "cost_center": "ENG",
      "procurement_status": "legal_review"
    },
    {
      "vendor_id": "signalnest",
      "name": "SignalNest Observability",
      "category": "monitoring",
      "annual_cost": 44500,
      "monthly_cost": 3708,
      "renewal_date": "2026-11-11",
      "status": "active",
      "owner": "Finance Ops",
      "termination_notice_days": 45,
      "auto_renew": false,
      "board_approved": true,
      "notes": "SignalNest Observability export row from ContractVault; owner attestation current.",
      "cost_center": "GTM",
      "procurement_status": "active_contract"
    },
    {
      "vendor_id": "fieldroute",
      "name": "FieldRoute Mobile",
      "category": "field ops",
      "annual_cost": 53000,
      "monthly_cost": 4417,
      "renewal_date": "2026-11-14",
      "status": "active",
      "owner": "Security",
      "termination_notice_days": 60,
      "auto_renew": true,
      "board_approved": true,
      "notes": "FieldRoute Mobile export row from ContractVault; owner attestation current.",
      "cost_center": "OPS",
      "procurement_status": "active_contract"
    },
    {
      "vendor_id": "protolab",
      "name": "PrototypeLab Systems",
      "category": "hardware",
      "annual_cost": 61500,
      "monthly_cost": 5125,
      "renewal_date": "2026-09-17",
      "status": "active",
      "owner": "Operations",
      "termination_notice_days": 75,
      "auto_renew": true,
      "board_approved": true,
      "notes": "PrototypeLab Systems export row from ContractVault; owner attestation current.",
      "cost_center": "SEC",
      "procurement_status": "active_contract"
    },
    {
      "vendor_id": "kitebase",
      "name": "Kitebase Warehouse",
      "category": "data",
      "annual_cost": 70000,
      "monthly_cost": 5833,
      "renewal_date": "2026-08-20",
      "status": "active",
      "owner": "Revenue",
      "termination_notice_days": 90,
      "auto_renew": false,
      "board_approved": true,
      "notes": "Kitebase Warehouse export row from ContractVault; owner attestation pending.",
      "cost_center": "FIN",
      "procurement_status": "active_contract"
    },
    {
      "vendor_id": "solarwisp",
      "name": "SolarWisp Materials",
      "category": "materials",
      "annual_cost": 78500,
      "monthly_cost": 6542,
      "renewal_date": "2026-07-23",
      "status": "active",
      "owner": "Data",
      "termination_notice_days": 30,
      "auto_renew": true,
      "board_approved": true,
      "notes": "SolarWisp Materials export row from ContractVault; owner attestation current.",
      "cost_center": "ENG",
      "procurement_status": "active_contract"
    },
    {
      "vendor_id": "skybridge",
      "name": "Skybridge Advisory",
      "category": "advisory",
      "annual_cost": 299000,
      "monthly_cost": 24917,
      "renewal_date": "2026-09-26",
      "status": "active",
      "owner": "People",
      "termination_notice_days": 45,
      "auto_renew": true,
      "board_approved": false,
      "notes": "Skybridge Advisory export row from ContractVault; owner attestation current.",
      "cost_center": "GTM",
      "procurement_status": "active_contract"
    },
    {
      "vendor_id": "voltagebay",
      "name": "VoltageBay QA",
      "category": "quality",
      "annual_cost": 95500,
      "monthly_cost": 7958,
      "renewal_date": "2026-11-09",
      "status": "pending_signature",
      "owner": "Platform",
      "termination_notice_days": 60,
      "auto_renew": false,
      "board_approved": true,
      "notes": "VoltageBay QA export row from ContractVault; owner attestation current.",
      "cost_center": "OPS",
      "procurement_status": "legal_review"
    },
    {
      "vendor_id": "meterloop",
      "name": "MeterLoop Telemetry",
      "category": "device ops",
      "annual_cost": 104000,
      "monthly_cost": 8667,
      "renewal_date": "2026-08-12",
      "status": "active",
      "owner": "Finance Ops",
      "termination_notice_days": 75,
      "auto_renew": true,
      "board_approved": true,
      "notes": "MeterLoop Telemetry export row from ContractVault; owner attestation pending.",
      "cost_center": "SEC",
      "procurement_status": "active_contract"
    },
    {
      "vendor_id": "gridledger",
      "name": "GridLedger Billing",
      "category": "finance ops",
      "annual_cost": 356000,
      "monthly_cost": 29667,
      "renewal_date": "2026-09-15",
      "status": "active",
      "owner": "Security",
      "termination_notice_days": 90,
      "auto_renew": true,
      "board_approved": true,
      "notes": "GridLedger Billing export row from ContractVault; owner attestation current.",
      "cost_center": "FIN",
      "procurement_status": "active_contract"
    },
    {
      "vendor_id": "sunharbor",
      "name": "SunHarbor Logistics",
      "category": "logistics",
      "annual_cost": 121000,
      "monthly_cost": 10083,
      "renewal_date": "2026-07-18",
      "status": "active",
      "owner": "Operations",
      "termination_notice_days": 30,
      "auto_renew": false,
      "board_approved": true,
      "notes": "SunHarbor Logistics export row from ContractVault; owner attestation current.",
      "cost_center": "ENG",
      "procurement_status": "active_contract"
    },
    {
      "vendor_id": "relayfox",
      "name": "RelayFox Security",
      "category": "security",
      "annual_cost": 129500,
      "monthly_cost": 10792,
      "renewal_date": "2026-11-21",
      "status": "active",
      "owner": "Revenue",
      "termination_notice_days": 45,
      "auto_renew": true,
      "board_approved": true,
      "notes": "RelayFox Security export row from ContractVault; owner attestation current.",
      "cost_center": "GTM",
      "procurement_status": "active_contract"
    },
    {
      "vendor_id": "workvine",
      "name": "WorkVine Recruiting",
      "category": "recruiting",
      "annual_cost": 413000,
      "monthly_cost": 34417,
      "renewal_date": "2026-08-24",
      "status": "active",
      "owner": "Data",
      "termination_notice_days": 60,
      "auto_renew": true,
      "board_approved": false,
      "notes": "WorkVine Recruiting export row from ContractVault; owner attestation pending.",
      "cost_center": "OPS",
      "procurement_status": "active_contract"
    },
    {
      "vendor_id": "plantline",
      "name": "PlantLine Support",
      "category": "support",
      "annual_cost": 146500,
      "monthly_cost": 12208,
      "renewal_date": "2026-11-27",
      "status": "active",
      "owner": "People",
      "termination_notice_days": 75,
      "auto_renew": false,
      "board_approved": true,
      "notes": "PlantLine Support export row from ContractVault; owner attestation current.",
      "cost_center": "SEC",
      "procurement_status": "active_contract"
    },
    {
      "vendor_id": "canopycalc",
      "name": "CanopyCalc Forecasting",
      "category": "analytics",
      "annual_cost": 155000,
      "monthly_cost": 12917,
      "renewal_date": "2026-11-10",
      "status": "pending_signature",
      "owner": "Platform",
      "termination_notice_days": 90,
      "auto_renew": true,
      "board_approved": true,
      "notes": "CanopyCalc Forecasting export row from ContractVault; owner attestation current.",
      "cost_center": "FIN",
      "procurement_status": "legal_review"
    },
    {
      "vendor_id": "arraydesk",
      "name": "ArrayDesk CRM",
      "category": "sales",
      "annual_cost": 163500,
      "monthly_cost": 13625,
      "renewal_date": "2026-07-13",
      "status": "active",
      "owner": "Finance Ops",
      "termination_notice_days": 30,
      "auto_renew": true,
      "board_approved": true,
      "notes": "ArrayDesk CRM export row from ContractVault; owner attestation current.",
      "cost_center": "ENG",
      "procurement_status": "active_contract"
    },
    {
      "vendor_id": "terraedge",
      "name": "TerraEdge Integrations",
      "category": "integration",
      "annual_cost": 172000,
      "monthly_cost": 14333,
      "renewal_date": "2026-08-16",
      "status": "active",
      "owner": "Security",
      "termination_notice_days": 45,
      "auto_renew": false,
      "board_approved": true,
      "notes": "TerraEdge Integrations export row from ContractVault; owner attestation pending.",
      "cost_center": "GTM",
      "procurement_status": "active_contract"
    },
    {
      "vendor_id": "brightcell",
      "name": "BrightCell Supply",
      "category": "supply chain",
      "annual_cost": 180500,
      "monthly_cost": 15042,
      "renewal_date": "2026-11-19",
      "status": "active",
      "owner": "Operations",
      "termination_notice_days": 60,
      "auto_renew": true,
      "board_approved": true,
      "notes": "BrightCell Supply export row from ContractVault; owner attestation current.",
      "cost_center": "OPS",
      "procurement_status": "active_contract"
    },
    {
      "vendor_id": "chargewell",
      "name": "ChargeWell Field Ops",
      "category": "field ops",
      "annual_cost": 527000,
      "monthly_cost": 43917,
      "renewal_date": "2026-09-22",
      "status": "active",
      "owner": "Revenue",
      "termination_notice_days": 75,
      "auto_renew": true,
      "board_approved": false,
      "notes": "ChargeWell Field Ops export row from ContractVault; owner attestation current.",
      "cost_center": "SEC",
      "procurement_status": "active_contract"
    },
    {
      "vendor_id": "reliantnest",
      "name": "ReliantNest Compliance",
      "category": "compliance",
      "annual_cost": 197500,
      "monthly_cost": 16458,
      "renewal_date": "2026-11-25",
      "status": "active",
      "owner": "Data",
      "termination_notice_days": 90,
      "auto_renew": false,
      "board_approved": true,
      "notes": "ReliantNest Compliance export row from ContractVault; owner attestation current.",
      "cost_center": "FIN",
      "procurement_status": "active_contract"
    }
  ]
}
